HISTORY.md
LICENSE
MANIFEST.in
README.md
setup.cfg
setup.py
kueventparser/__init__.py
kueventparser/__version__.py
kueventparser/api.py
kueventparser/core.py
kueventparser/events.py
kueventparser/utils.py
kueventparser.egg-info/PKG-INFO
kueventparser.egg-info/SOURCES.txt
kueventparser.egg-info/dependency_links.txt
kueventparser.egg-info/entry_points.txt
kueventparser.egg-info/not-zip-safe
kueventparser.egg-info/requires.txt
kueventparser.egg-info/top_level.txt
kueventparser/adapters/__init__.py
kueventparser/adapters/base.py
kueventparser/adapters/official.py
tests/__init__.py
tests/conftest.py
tests/test_adapters.py
tests/test_utils.py