Metadata-Version: 2.1
Name: kueventparser
Version: 3.0.1
Summary: event parser of kyoto-univ.
Home-page: https://github.com/kkiyama117/KUEventParser
Author: kkiyama117
Author-email: k.kiyama117@gmail.com
Maintainer:  Unimap, Inc.
Maintainer-email: info@unimap.co.jp
License: MIT
Platform: UNKNOWN
Classifier: Development Status :: 5 - Production/Stable
Classifier: Environment :: Plugins
Classifier: Environment :: Console
Classifier: Intended Audience :: Developers
Classifier: Natural Language :: Japanese
Classifier: License :: OSI Approved :: Apache Software License
Classifier: Programming Language :: Python
Classifier: Programming Language :: Python :: 3
Classifier: Programming Language :: Python :: 3.4
Classifier: Programming Language :: Python :: 3.5
Classifier: Programming Language :: Python :: 3.6
Classifier: Programming Language :: Python :: 3.7
Classifier: Programming Language :: Python :: Implementation :: CPython
Classifier: Programming Language :: Python :: Implementation :: PyPy
Classifier: Topic :: Internet :: WWW/HTTP :: Indexing/Search
Classifier: Topic :: Utilities
Requires-Python: >=3.4
